<?xml version="1.0" encoding="utf-8"?>
<!DOCTYPE hibernate-mapping PUBLIC "-//Hibernate/Hibernate Mapping DTD 3.0//EN"
"http://hibernate.sourceforge.net/hibernate-mapping-3.0.dtd">
<!-- 
    Mapping file autogenerated by MyEclipse Persistence Tools
-->
<hibernate-mapping>
    <class name="com.zgld.api.beans.YGoods" table="Y_Goods" schema="dbo" >
        <id name="goId" type="java.lang.Integer">
            <column name="Go_ID" />
            <generator class="identity" />
        </id>
        <property name="unitSetId" type="java.lang.Integer">
            <column name="Unit_Set_ID" />
        </property>
        <property name="accountActId" type="java.lang.Integer">
            <column name="Account_Act_ID" />
        </property>
        <property name="shipId" type="java.lang.Integer">
            <column name="Ship_ID" />
        </property>
        <property name="goClassSetId" type="java.lang.Integer">
            <column name="Go_Class_Set_ID" />
        </property>
        <property name="goBrandSetId" type="java.lang.Integer">
            <column name="Go_Brand_Set_ID" />
        </property>
        <property name="goName" type="java.lang.String">
            <column name="Go_Name" />
        </property>
        <property name="goKeywords" type="java.lang.String">
            <column name="Go_Keywords" />
        </property>
        <property name="goIntro" type="java.lang.String">
            <column name="Go_Intro" />
        </property>
        <property name="goDetail" type="java.lang.String">
            <column name="Go_Detail" />
        </property>
        <property name="goMobileDetail" type="java.lang.String">
            <column name="Go_Mobile_Detail" />
        </property>
        <property name="goNumber" type="java.lang.String">
            <column name="Go_Number" />
        </property>
        <property name="goSellCount" type="java.lang.Integer">
            <column name="Go_Sell_Count" />
        </property>
        <property name="goCount" type="java.lang.Integer">
            <column name="Go_Count" />
        </property>
        <property name="goHits" type="java.lang.Integer">
            <column name="Go_Hits" />
        </property>
        <property name="goBidPrice" type="java.lang.Double">
            <column name="Go_Bid_Price" scale="4" />
        </property>
        <property name="goSalePrice" type="java.lang.Double">
            <column name="Go_Sale_Price" scale="4" not-null="true" />
        </property>
        <property name="goThumb" type="java.lang.String">
            <column name="Go_Thumb" />
        </property>
        <property name="goFreeShipping" type="java.lang.Integer">
            <column name="Go_Free_Shipping" />
        </property>
        <property name="goIsNew" type="java.lang.Integer">
            <column name="Go_Is_New" />
        </property>
        <property name="goIsHot" type="java.lang.Integer">
            <column name="Go_Is_Hot" />
        </property>
        <property name="goIsState" type="java.lang.Integer">
            <column name="Go_Is_State" />
        </property>
        <property name="goIsPromote" type="java.lang.Integer">
            <column name="Go_Is_Promote" />
        </property>
        <property name="goOrder" type="java.lang.Integer">
            <column name="Go_Order" />
        </property>
        <property name="goTopOrder" type="java.lang.Integer">
            <column name="Go_Top_Order" />
        </property>
        <property name="isDelete" type="java.lang.Integer">
            <column name="Is_Delete" />
        </property>
        <property name="goTime" type="java.util.Date">
            <column name="Go_Time" length="16" not-null="true" />
        </property>
    </class>
</hibernate-mapping>
