<?xml version="1.0" encoding="utf-8"?>
<!DOCTYPE hibernate-mapping PUBLIC "-//Hibernate/Hibernate Mapping DTD 3.0//EN"
"http://www.hibernate.org/dtd/hibernate-mapping-3.0.dtd">
<!-- 
    Mapping file autogenerated by MyEclipse Persistence Tools
-->
<hibernate-mapping>
    <class name="com.zgld.api.beans.YRebateRelation" table="Y_Rebate_Relation" schema="dbo" catalog="www.shop.com">
        <id name="rebateRelationId" type="java.lang.Integer">
            <column name="Rebate_Relation_ID" />
            <generator class="identity" />
        </id>
        <property name="parentUserId" type="java.lang.Integer">
            <column name="Parent_User_ID" />
        </property>
        <property name="currentUserId" type="java.lang.Integer">
            <column name="Current_User_ID" />
        </property>
    </class>
</hibernate-mapping>
